Source/src/maxpool.sv
module maxpool (
    input wire clk,
    input wire rst,
    input wire[11:0] data_in, // Data in type Q4.8
    input wire end_data,
    output reg finish,
    output reg[11:0] out // Data out type Q4.8
);
    reg sync;
    initial sync = 0;

    always @(posedge clk or posedge rst) begin
        if (rst) begin
            finish <= 0;
            sync <=0;
            out <= 0;
        end else if (end_data) begin
            finish <= 1;
        end
        else begin
            if(sync) out <= (data_in > out) ? data_in : out;
            else sync <=1;
        end
    end
endmodule

Source/tb/tb_maxpool.sv
`timescale 1ns/1ps

module maxpool_tb;
    reg clk = 0;
    reg rst = 1;
    reg [11:0] data_in;
    reg end_data;
    wire finish;
    wire [11:0] out;
    
    // Clock generation
    always #5 clk = ~clk;
    
    // Instantiate DUT
    maxpool dut (
        .clk(clk),
        .rst(rst),
        .data_in(data_in),
        .end_data(end_data),
        .finish(finish),
        .out(out)
    );
    
    initial begin
        // Initialize waveform dump
        $dumpfile("maxpool.vcd");
        $dumpvars(0, maxpool_tb);
        
        // Reset sequence
        #10 rst = 0;
        
        // Test Case 1: Basic 2x2 window
        $display("Test Case 1: Basic window");
        data_in = 12'h100; // 1.0 in Q4.8
        #10 data_in = 12'h080; // 0.5
        #10 data_in = 12'h180; // 1.5
        #10 data_in = 12'h000; // 0.0
        end_data = 1;
        #10 end_data = 0;
        #20; // Wait for processing
        
        // Test Case 2: Boundary values
        $display("Test Case 2: Boundary values");
        data_in = 12'h7FF; // Max Q4.8 (7.996)
        #10 data_in = 12'h000; 
        #10 data_in = 12'h7FF;
        #10 data_in = 12'h700;
        end_data = 1;
        #10 end_data = 0;
        #20;
        
    
        // Test Case 3: Reset during operation
        $display("Test Case 3: Reset during operation");
        data_in = 12'h100;
        #10 data_in = 12'h200;
        #5 rst = 1;
        #5 rst = 0;
        #10 data_in = 12'h300;
        #10 data_in = 12'h400;
        end_data = 1;
        #10 end_data = 0;
        #20;
        
        $display("All tests completed");
        $finish;
    end
endmodule

Source/sim/maxpool.vcd
$date
	Fri Apr 18 14:01:07 2025
$end
$version
	ModelSim Version 10.1d
$end
$timescale
	1ps
$end
$scope module maxpool_tb $end
$var reg 1 ! clk $end
$var reg 1 " rst $end
$var reg 12 # data_in [11:0] $end
$var reg 1 $ end_data $end
$var wire 1 % finish $end
$var wire 1 & out [11] $end
$var wire 1 ' out [10] $end
$var wire 1 ( out [9] $end
$var wire 1 ) out [8] $end
$var wire 1 * out [7] $end
$var wire 1 + out [6] $end
$var wire 1 , out [5] $end
$var wire 1 - out [4] $end
$var wire 1 . out [3] $end
$var wire 1 / out [2] $end
$var wire 1 0 out [1] $end
$var wire 1 1 out [0] $end
$scope module dut $end
$var wire 1 2 clk $end
$var wire 1 3 rst $end
$var wire 1 4 data_in [11] $end
$var wire 1 5 data_in [10] $end
$var wire 1 6 data_in [9] $end
$var wire 1 7 data_in [8] $end
$var wire 1 8 data_in [7] $end
$var wire 1 9 data_in [6] $end
$var wire 1 : data_in [5] $end
$var wire 1 ; data_in [4] $end
$var wire 1 < data_in [3] $end
$var wire 1 = data_in [2] $end
$var wire 1 > data_in [1] $end
$var wire 1 ? data_in [0] $end
$var wire 1 @ end_data $end
$var reg 1 A finish $end
$var reg 12 B out [11:0] $end
$var reg 1 C sync $end
$upscope $end
$upscope $end
$enddefinitions $end
#0
$dumpvars
0!
1"
bx #
x$
0A
b0 B
0C
0%
01
00
0/
0.
0-
0,
0+
0*
0)
0(
0'
0&
02
13
x?
x>
x=
x<
x;
x:
x9
x8
x7
x6
x5
x4
x@
$end
#5000
1!
12
#10000
0"
b100000000 #
0!
0?
0>
0=
0<
0;
0:
09
08
17
06
05
04
03
02
#15000
1!
12
1C
#20000
b10000000 #
0!
18
07
02
#25000
1!
12
b10000000 B
1*
#30000
b110000000 #
0!
17
02
#35000
1!
12
b110000000 B
1)
#40000
b0 #
1$
0!
08
07
1@
02
#45000
1!
12
1A
1%
#50000
0$
0!
0@
02
#55000
1!
12
#60000
0!
02
#65000
1!
12
#70000
b11111111111 #
0!
1?
1>
1=
1<
1;
1:
19
18
17
16
15
02
#75000
1!
12
b11111111111 B
11
10
1/
1.
1-
1,
1+
1(
1'
#80000
b0 #
0!
0?
0>
0=
0<
0;
0:
09
08
07
06
05
02
#85000
1!
12
#90000
b11111111111 #
0!
1?
1>
1=
1<
1;
1:
19
18
17
16
15
02
#95000
1!
12
#100000
b11100000000 #
1$
0!
0?
0>
0=
0<
0;
0:
09
08
1@
02
#105000
1!
12
#110000
0$
0!
0@
02
#115000
1!
12
#120000
0!
02
#125000
1!
12
#130000
b100000000 #
0!
06
05
02
#135000
1!
12
#140000
b1000000000 #
0!
07
16
02
#145000
1"
1!
13
12
0A
0C
b0 B
0%
01
00
0/
0.
0-
0,
0+
0*
0)
0(
0'
#150000
0"
0!
03
02
#155000
1!
12
1C
#160000
b1100000000 #
0!
17
02
#165000
1!
12
b1100000000 B
1)
1(
#170000
b10000000000 #
1$
0!
07
06
15
1@
02
#175000
1!
12
1A
1%
#180000
0$
0!
0@
02
#185000
1!
12
b10000000000 B
0)
0(
1'
